codesnip/__init__.py
codesnip/admin.py
codesnip/apps.py
codesnip/forms.py
codesnip/models.py
codesnip/settings.py
codesnip/views.py
codesnip/migrations/0001_initial.py
codesnip/migrations/__init__.py
codesnip/templatetags/__init__.py
codesnip/templatetags/codesnip.py
django_codesnip-0.2.3.dist-info/DESCRIPTION.rst
django_codesnip-0.2.3.dist-info/METADATA
django_codesnip-0.2.3.dist-info/RECORD
django_codesnip-0.2.3.dist-info/WHEEL
django_codesnip-0.2.3.dist-info/metadata.json
django_codesnip-0.2.3.dist-info/top_level.txt
tests/__init__.py
tests/conftest.py
tests/test_forms.py
tests/test_models.py
tests/test_templatetags.py
tests/utils.py
